LICENSE
MANIFEST.in
README.rst
setup.cfg
setup.py
docs/Makefile
docs/buttons.rst
docs/conf.py
docs/graphics.rst
docs/hardware.rst
docs/index.rst
docs/readme.rst
docs/reference.rst
docs/runloop.rst
docs/settings.rst
docs/sound.rst
docs/touch.rst
docs/webhooks.rst
tbtool/__init__.py
tbtool/__main__.py
tbtool/appdirs.py
tbtool/tingbot.key
tbtool/tingbot.key.pub
tests/GifSample.gif
tests/__init__.py
tests/blank.png
tests/button_test.py
tests/cache_test.py
tests/hardware_test.py
tests/tingapp_test.py
tests/typesetter_tests.py
tingbot/__init__.py
tingbot/audio.py
tingbot/button.py
tingbot/cache.py
tingbot/error.py
tingbot/graphics.py
tingbot/hardware.py
tingbot/input.py
tingbot/quit.py
tingbot/run_loop.py
tingbot/tingapp.py
tingbot/typesetter.py
tingbot/utils.py
tingbot/web.py
tingbot/platform_specific/__init__.py
tingbot/platform_specific/bot.png
tingbot/platform_specific/bot@2x.png
tingbot/platform_specific/osx.py
tingbot/platform_specific/sdl_wrapper.py
tingbot/platform_specific/simulator-icon.png
tingbot/platform_specific/tingbot.py
tingbot/resources/04B_03__.TTF
tingbot/resources/Geneva.ttf
tingbot/resources/MiniSet2.ttf
tingbot/resources/broken_image.png
tingbot/resources/default-icon-texture-96.png
tingbot_python.egg-info/PKG-INFO
tingbot_python.egg-info/SOURCES.txt
tingbot_python.egg-info/dependency_links.txt
tingbot_python.egg-info/entry_points.txt
tingbot_python.egg-info/not-zip-safe
tingbot_python.egg-info/requires.txt
tingbot_python.egg-info/top_level.txt