Metadata-Version: 1.1
Name: tingbot-python
Version: 1.2.1
Summary: Python APIs to write apps for Tingbot
Home-page: https://github.com/tingbot/tingbot-python
Author: Joe Rickerby
Author-email: joerick@mac.com
License: BSD
Keywords: tingbot
Platform: UNKNOWN
Classifier: Intended Audience :: Developers
Classifier: Natural Language :: English
Classifier: Programming Language :: Python :: 2
Classifier: Programming Language :: Python :: 2.7
Obsoletes: tingbot
